portalbrasil/intranet/__init__.py
portalbrasil/intranet/configure.zcml
portalbrasil/intranet/dependencies.zcml
portalbrasil/intranet/distributions.zcml
portalbrasil/intranet/handlers.py
portalbrasil/intranet/interfaces.py
portalbrasil/intranet/permissions.zcml
portalbrasil/intranet/profiles.zcml
portalbrasil/intranet/testing.py
portalbrasil/intranet/behaviors/__init__.py
portalbrasil/intranet/behaviors/configure.zcml
portalbrasil/intranet/behaviors/contato.py
portalbrasil/intranet/behaviors/endereco.py
portalbrasil/intranet/behaviors/matricula.py
portalbrasil/intranet/content/__init__.py
portalbrasil/intranet/content/area.py
portalbrasil/intranet/content/colaborador.py
portalbrasil/intranet/content/servico.py
portalbrasil/intranet/controlpanel/__init__.py
portalbrasil/intranet/controlpanel/configure.zcml
portalbrasil/intranet/distributions/intranet/image.png
portalbrasil/intranet/distributions/intranet/profiles.json
portalbrasil/intranet/distributions/intranet/schema.json
portalbrasil/intranet/distributions/intranet/content/discussions.json
portalbrasil/intranet/distributions/intranet/content/portlets.json
portalbrasil/intranet/distributions/intranet/content/principals.json
portalbrasil/intranet/distributions/intranet/content/redirects.json
portalbrasil/intranet/distributions/intranet/content/relations.json
portalbrasil/intranet/distributions/intranet/content/translations.json
portalbrasil/intranet/distributions/intranet/content/content/__metadata__.json
portalbrasil/intranet/distributions/intranet/content/content/0f37fe34245f439ba78901e36f6da9dc/data.json
portalbrasil/intranet/distributions/intranet/content/content/26e5fc286fce4c2e9613411cc0f0663f/data.json
portalbrasil/intranet/distributions/intranet/content/content/42bb0222abfe4356949de633f5cc25e6/data.json
portalbrasil/intranet/distributions/intranet/content/content/87b599b4dd5a419da58c59632bace85c/data.json
portalbrasil/intranet/distributions/intranet/content/content/abcd08c1843b4540b90cb73b9e9fc050/data.json
portalbrasil_intranet-1.0.0b3.dist-info/METADATA
portalbrasil_intranet-1.0.0b3.dist-info/WHEEL
portalbrasil_intranet-1.0.0b3.dist-info/entry_points.txt
portalbrasil_intranet-1.0.0b3.dist-info/licenses/LICENSE.GPL
portalbrasil_intranet-1.0.0b3.dist-info/licenses/LICENSE.md
portalbrasil_intranet-1.0.0b3.dist-info/RECORD
