Metadata-Version: 2.4
Name: portalbrasil.intranet
Version: 1.0.0b3
Summary: Solução de Intranet construída com PortalBrasil
Project-URL: Homepage, https://github.com/portal-br/intranet
Project-URL: PyPI, https://pypi.org/project/portalbrasil.intranet
Project-URL: Source, https://github.com/portal-br/intranet
Project-URL: Tracker, https://github.com/portal-br/intranet/issues
Author-email: PloneGov-BR <gov@plone.org.br>
License-Expression: GPL-2.0-only
License-File: LICENSE.GPL
License-File: LICENSE.md
Keywords: CMS,Intranet,Plone,PortalBrasil
Classifier: Development Status :: 3 - Alpha
Classifier: Environment :: Web Environment
Classifier: Framework :: Plone
Classifier: Framework :: Plone :: 6.1
Classifier: Framework :: Plone :: Addon
Classifier: License :: OSI Approved :: GNU General Public License v2 (GPLv2)
Classifier: Operating System :: OS Independent
Classifier: Programming Language :: Python
Classifier: Programming Language :: Python :: 3.12
Classifier: Programming Language :: Python :: 3.13
Requires-Python: >=3.12
Requires-Dist: collective-bookmarks
Requires-Dist: collective-honeypot
Requires-Dist: collective-taxonomy
Requires-Dist: collective-volto-formsupport
Requires-Dist: collective-volto-otp
Requires-Dist: plone-app-discussion
Requires-Dist: portalbrasil-core==1.0.0a5
Provides-Extra: test
Requires-Dist: horse-with-no-namespace>=20250408.0; extra == 'test'
Requires-Dist: mypy>=1.15.0; extra == 'test'
Requires-Dist: plone-app-testing; extra == 'test'
Requires-Dist: plone-restapi[test]; extra == 'test'
Requires-Dist: pytest; extra == 'test'
Requires-Dist: pytest-cov==6.1.1; extra == 'test'
Requires-Dist: pytest-plone>=1.0.0a1; extra == 'test'
